arptools/__init__.py
arptools/__init__.pyi
arptools/__main__.py
arptools/cli.py
arptools/network.py
arptools/py.typed
arptools/arp/__init__.py
arptools/arp/announcement.py
arptools/arp/garp.py
arptools/arp/probe.py
arptools/arp/pscan.py
arptools/arp/scan.py
arptools/arp/packets/__init__.py
arptools/arp/packets/reply.py
arptools/arp/packets/request.py
arptools/modules/__init__.py
arptools/modules/ansi.py
arptools/modules/log.py
arptools/modules/metadata.py
arptools/modules/utils.py
arptools/modules/ascii/__init__.py
arptools/modules/ascii/animation.py
arptools/modules/parsing/__init__.py
arptools/modules/parsing/parents.py
arptools/modules/parsing/parsers/__init__.py
arptools/modules/parsing/parsers/main.py
arptools/parsers/__init__.py
arptools/parsers/arpa.py
arptools/parsers/arpr.py
arptools/parsers/arprobe.py
arptools/parsers/arpscan.py
arptools/parsers/garp.py
arptools/parsers/types.py
arptools-0.1.1.dist-info/LICENSE
arptools-0.1.1.dist-info/METADATA
arptools-0.1.1.dist-info/WHEEL
arptools-0.1.1.dist-info/entry_points.txt
arptools-0.1.1.dist-info/top_level.txt
arptools-0.1.1.dist-info/RECORD
