Metadata-Version: 2.1
Name: arptools
Version: 0.1.1
Summary: CLI tools to do network analysis with ARP packets.
Author-email: Stefano Cuizza <stefano.cuizza@protonmail.com>
Maintainer-email: Stefano Cuizza <stefano.cuizza@protonmail.com>
License:                     GNU GENERAL PUBLIC LICENSE
Project-URL: Github, https://github.com/x55xaa/arptools
Keywords: arp protocol,networking
Classifier: Development Status :: 4 - Beta
Classifier: Intended Audience :: End Users/Desktop
Classifier: License :: OSI Approved :: GNU General Public License v3 (GPLv3)
Classifier: Operating System :: POSIX :: Linux
Classifier: Topic :: Security
Classifier: Topic :: System :: Networking :: Monitoring
Requires-Python: >=3.12
License-File: LICENSE
Requires-Dist: asciimatics
Requires-Dist: colorama
Requires-Dist: scapy
Provides-Extra: docs
Requires-Dist: myst_parser; extra == "docs"
Requires-Dist: sphinx; extra == "docs"
Requires-Dist: sphinx-argparse; extra == "docs"
Requires-Dist: sphinx_autodoc_typehints; extra == "docs"
Requires-Dist: sphinx_rtd_theme; extra == "docs"
Provides-Extra: testing
Requires-Dist: pylint; extra == "testing"
Requires-Dist: pytest; extra == "testing"
Requires-Dist: pytest-cov; extra == "testing"
Requires-Dist: ruff; extra == "testing"
Requires-Dist: tox; extra == "testing"
